LICENSE.txt
MANIFEST.in
README.rst
setup.py
DhelmGfeedClient/__init__.py
DhelmGfeedClient/constants.py
DhelmGfeedClient/gfeedclient.py
DhelmGfeedClient.egg-info/PKG-INFO
DhelmGfeedClient.egg-info/SOURCES.txt
DhelmGfeedClient.egg-info/dependency_links.txt
DhelmGfeedClient.egg-info/requires.txt
DhelmGfeedClient.egg-info/top_level.txt
docs/_build/html/.buildinfo
docs/_build/html/DhelmGfeedClient.html
docs/_build/html/genindex.html
docs/_build/html/index.html
docs/_build/html/modules.html
docs/_build/html/objects.inv
docs/_build/html/py-modindex.html
docs/_build/html/search.html
docs/_build/html/searchindex.js
docs/_build/html/_sources/DhelmGfeedClient.rst.txt
docs/_build/html/_sources/index.rst.txt
docs/_build/html/_sources/modules.rst.txt
docs/_build/html/_static/ajax-loader.gif
docs/_build/html/_static/basic.css
docs/_build/html/_static/classic.css
docs/_build/html/_static/comment-bright.png
docs/_build/html/_static/comment-close.png
docs/_build/html/_static/comment.png
docs/_build/html/_static/doctools.js
docs/_build/html/_static/documentation_options.js
docs/_build/html/_static/down-pressed.png
docs/_build/html/_static/down.png
docs/_build/html/_static/file.png
docs/_build/html/_static/jquery-3.2.1.js
docs/_build/html/_static/jquery.js
docs/_build/html/_static/minus.png
docs/_build/html/_static/plus.png
docs/_build/html/_static/pygments.css
docs/_build/html/_static/searchtools.js
docs/_build/html/_static/sidebar.js
docs/_build/html/_static/underscore-1.3.1.js
docs/_build/html/_static/underscore.js
docs/_build/html/_static/up-pressed.png
docs/_build/html/_static/up.png
docs/_build/html/_static/websupport.js