Metadata-Version: 2.1
Name: DhelmGfeedClient
Version: 1.0.2
Summary: This is a python client for websocket APIs provided by Global Financial Datafeeds LLP to access financial data.
Home-page: https://github.com/kncsolutions/dhelm-gfeed-python-client
Author: Pallav Nandi Chaudhuri
Author-email: developer@kncsolutions.in
License: Apache License, Version 2.0
Project-URL: Bug Reports, https://github.com/kncsolutions/dhelm-gfeed-python-client/issues
Project-URL: Source, https://github.com/kncsolutions/dhelm-gfeed-python-client
Platform: UNKNOWN
Classifier: Development Status :: 4 - Beta
Classifier: Intended Audience :: End Users/Desktop
Classifier: Intended Audience :: Developers
Classifier: Topic :: Office/Business :: Financial :: Investment
Classifier: Topic :: Software Development :: Libraries :: Python Modules
Classifier: Programming Language :: Python :: 3.4
Classifier: Operating System :: OS Independent
Classifier: License :: OSI Approved :: Apache Software License
Provides-Extra: doc
